paypalcheckoutsdk/__init__.py
paypalcheckoutsdk/config.py
paypalcheckoutsdk/core/__init__.py
paypalcheckoutsdk/core/access_token.py
paypalcheckoutsdk/core/access_token_request.py
paypalcheckoutsdk/core/environment.py
paypalcheckoutsdk/core/paypal_http_client.py
paypalcheckoutsdk/core/refresh_token_request.py
paypalcheckoutsdk/core/util.py
paypalcheckoutsdk/orders/__init__.py
paypalcheckoutsdk/orders/orders_authorize_request.py
paypalcheckoutsdk/orders/orders_capture_request.py
paypalcheckoutsdk/orders/orders_create_request.py
paypalcheckoutsdk/orders/orders_get_request.py
paypalcheckoutsdk/orders/orders_patch_request.py
paypalcheckoutsdk/orders/orders_validate_request.py
paypalcheckoutsdk/payments/__init__.py
paypalcheckoutsdk/payments/authorizations_capture_request.py
paypalcheckoutsdk/payments/authorizations_get_request.py
paypalcheckoutsdk/payments/authorizations_reauthorize_request.py
paypalcheckoutsdk/payments/authorizations_void_request.py
paypalcheckoutsdk/payments/captures_get_request.py
paypalcheckoutsdk/payments/captures_refund_request.py
paypalcheckoutsdk/payments/refunds_get_request.py
sample/AuthorizeIntentExamples/__init__.py
sample/AuthorizeIntentExamples/authorize_order.py
sample/AuthorizeIntentExamples/capture_order.py
sample/AuthorizeIntentExamples/create_order.py
sample/AuthorizeIntentExamples/run_all.py
sample/CaptureIntentExamples/__init__.py
sample/CaptureIntentExamples/capture_order.py
sample/CaptureIntentExamples/create_order.py
sample/CaptureIntentExamples/run_all.py
tests/core/__init__.py
tests/core/paypal_http_client_test.py
tests/core/paypaltestharness.py
tests/orders/__init__.py
tests/orders/orders_authorize_test.py
tests/orders/orders_capture_test.py
tests/orders/orders_create_test.py
tests/orders/orders_get_test.py
tests/orders/orders_patch_test.py
tests/orders/orders_validate_test.py
tests/payments/__init__.py
tests/payments/authorizations_capture_test.py
tests/payments/authorizations_get_test.py
raja_test_package-1.0.6.dist-info/LICENSE
raja_test_package-1.0.6.dist-info/METADATA
raja_test_package-1.0.6.dist-info/WHEEL
raja_test_package-1.0.6.dist-info/top_level.txt
raja_test_package-1.0.6.dist-info/RECORD
