Metadata-Version: 2.1
Name: raja-test-package
Version: 1.0.6
Summary: Python Rest SDK for PayPal Checkout
Home-page: https://github.com/paypal/Checkout-Python-SDK/
Author: Ganeshram Chockalingam
Author-email: gchockalingam@paypal.com
License: UNKNOWN
Platform: UNKNOWN
Classifier: Programming Language :: Python :: 2
Classifier: Programming Language :: Python :: 3
Classifier: License :: OSI Approved :: MIT License
Classifier: Operating System :: OS Independent
Requires-Dist: braintreehttp
